CHANGES.txt
MANIFEST.in
README.md
package.json
setup.py
GeobricksRESTEngine.egg-info/PKG-INFO
GeobricksRESTEngine.egg-info/SOURCES.txt
GeobricksRESTEngine.egg-info/dependency_links.txt
GeobricksRESTEngine.egg-info/pbr.json
GeobricksRESTEngine.egg-info/requires.txt
GeobricksRESTEngine.egg-info/top_level.txt
geobricks_rest_engine/__init__.py
geobricks_rest_engine/__init__.pyc
geobricks_rest_engine/config/__init__.py
geobricks_rest_engine/config/__init__.pyc
geobricks_rest_engine/config/common_settings.py
geobricks_rest_engine/config/common_settings.pyc
geobricks_rest_engine/config/rest_settings.py
geobricks_rest_engine/config/rest_settings.pyc
geobricks_rest_engine/core/__init__.py
geobricks_rest_engine/core/__init__.pyc
geobricks_rest_engine/core/log.py
geobricks_rest_engine/core/log.pyc
geobricks_rest_engine/core/utils.py
geobricks_rest_engine/core/utils.pyc
geobricks_rest_engine/rest/__init__.py
geobricks_rest_engine/rest/engine.py