Metadata-Version: 1.0
Name: GeobricksRESTEngine
Version: 0.1.11
Summary: Common entry point for Geobricks REST services.
Home-page: http://pypi.python.org/pypi/GeobricksRESTEngine/
Author: Simone Murzilli; Guido Barbaglia
Author-email: geobrickspy@gmail.com
License: LICENSE.txt
Platform: UNKNOWN
